chuk_mcp_math_server/__init__.py
chuk_mcp_math_server/cli.py
chuk_mcp_math_server/config.py
chuk_mcp_math_server/function_filter.py
chuk_mcp_math_server/math_config.py
chuk_mcp_math_server/math_server.py
chuk_mcp_math_server-0.3.3.dist-info/licenses/LICENSE
chuk_mcp_math_server-0.3.3.dist-info/METADATA
chuk_mcp_math_server-0.3.3.dist-info/WHEEL
chuk_mcp_math_server-0.3.3.dist-info/entry_points.txt
chuk_mcp_math_server-0.3.3.dist-info/top_level.txt
chuk_mcp_math_server-0.3.3.dist-info/RECORD
