Metadata-Version: 2.4
Name: chuk-mcp-math-server
Version: 0.3.3
Summary: Configurable mathematical computation server for MCP protocol
Author-email: Chuk AI Team <chrishayuk@somejunkmailbox.com>
License-Expression: MIT
Project-URL: Homepage, https://github.com/chuk-mcp/chuk-mcp-math-server
Project-URL: Documentation, https://github.com/chuk-mcp/chuk-mcp-math-server/blob/main/README.md
Project-URL: Repository, https://github.com/chuk-mcp/chuk-mcp-math-server.git
Project-URL: Issues, https://github.com/chuk-mcp/chuk-mcp-math-server/issues
Classifier: Development Status :: 4 - Beta
Classifier: Intended Audience :: Developers
Classifier: Programming Language :: Python :: 3
Classifier: Programming Language :: Python :: 3.11
Classifier: Programming Language :: Python :: 3.12
Classifier: Topic :: Scientific/Engineering :: Mathematics
Classifier: Topic :: Software Development :: Libraries :: Python Modules
Requires-Python: >=3.11
License-File: LICENSE
Requires-Dist: chuk-mcp-math>=0.2.3
Requires-Dist: chuk-mcp-server>=0.15.1
Requires-Dist: pydantic>=2.0
Requires-Dist: pyyaml>=6.0.2
Provides-Extra: dev
Requires-Dist: pytest>=7.0.0; extra == "dev"
Requires-Dist: pytest-asyncio>=0.21.0; extra == "dev"
Requires-Dist: pytest-cov>=4.0.0; extra == "dev"
Requires-Dist: ruff>=0.1.0; extra == "dev"
Requires-Dist: mypy>=1.0.0; extra == "dev"
Requires-Dist: twine>=4.0.0; extra == "dev"
Requires-Dist: build>=1.0.0; extra == "dev"
Provides-Extra: full
Requires-Dist: chuk-mcp-math-server[dev]; extra == "full"
Dynamic: license-file
